{
  "width": 960,
  "height": 540,
  "nodes": [
    {
      "nodeId": "title_000",
      "parentId": null,
      "type": "Title",
      "level": 3,
      "bbox": {
        "x": 268.8,
        "y": 24,
        "w": 422.4,
        "h": 56
      }
    },
    {
      "nodeId": "panel_000",
      "parentId": "screen_0000",
      "type": "Panel",
      "level": 2,
      "bbox": {
        "x": 53.0,
        "y": 105.0,
        "w": 181.5,
        "h": 99.67
      }
    },
    {
      "nodeId": "panel_000_title",
      "parentId": "panel_000",
      "type": "Title",
      "level": 3,
      "bbox": {
        "x": 71.0,
        "y": 115.0,
        "w": 120,
        "h": 34
      }
    },
    {
      "nodeId": "panel_000_content",
      "parentId": "panel_000",
      "type": "Map",
      "level": 4,
      "bbox": {
        "x": 75.0,
        "y": 163.0,
        "w": 137.5,
        "h": 21.67
      }
    },
    {
      "nodeId": "panel_001",
      "parentId": "screen_0000",
      "type": "Panel",
      "level": 2,
      "bbox": {
        "x": 267.5,
        "y": 113.0,
        "w": 202.5,
        "h": 111.67
      }
    },
    {
      "nodeId": "panel_001_title",
      "parentId": "panel_001",
      "type": "Title",
      "level": 3,
      "bbox": {
        "x": 285.5,
        "y": 123.0,
        "w": 120,
        "h": 34
      }
    },
    {
      "nodeId": "panel_001_content",
      "parentId": "panel_001",
      "type": "Chart",
      "level": 4,
      "bbox": {
        "x": 289.5,
        "y": 171.0,
        "w": 158.5,
        "h": 33.67
      }
    },
    {
      "nodeId": "panel_002",
      "parentId": "screen_0000",
      "type": "Panel",
      "level": 2,
      "bbox": {
        "x": 492.0,
        "y": 113.0,
        "w": 188.5,
        "h": 119.67
      }
    },
    {
      "nodeId": "panel_002_title",
      "parentId": "panel_002",
      "type": "Title",
      "level": 3,
      "bbox": {
        "x": 510.0,
        "y": 123.0,
        "w": 120,
        "h": 34
      }
    },
    {
      "nodeId": "panel_002_content",
      "parentId": "panel_002",
      "type": "Table",
      "level": 4,
      "bbox": {
        "x": 514.0,
        "y": 171.0,
        "w": 144.5,
        "h": 41.67
      }
    },
    {
      "nodeId": "panel_003",
      "parentId": "screen_0000",
      "type": "Panel",
      "level": 2,
      "bbox": {
        "x": 714.5,
        "y": 116.0,
        "w": 186.5,
        "h": 101.67
      }
    },
    {
      "nodeId": "panel_003_title",
      "parentId": "panel_003",
      "type": "Title",
      "level": 3,
      "bbox": {
        "x": 732.5,
        "y": 126.0,
        "w": 120,
        "h": 34
      }
    },
    {
      "nodeId": "panel_003_content",
      "parentId": "panel_003",
      "type": "Table",
      "level": 4,
      "bbox": {
        "x": 736.5,
        "y": 174.0,
        "w": 142.5,
        "h": 23.67
      }
    },
    {
      "nodeId": "panel_004",
      "parentId": "screen_0000",
      "type": "Panel",
      "level": 2,
      "bbox": {
        "x": 52.0,
        "y": 245.67,
        "w": 181.5,
        "h": 129.67
      }
    },
    {
      "nodeId": "panel_004_title",
      "parentId": "panel_004",
      "type": "Title",
      "level": 3,
      "bbox": {
        "x": 70.0,
        "y": 255.67,
        "w": 120,
        "h": 34
      }
    },
    {
      "nodeId": "panel_004_content",
      "parentId": "panel_004",
      "type": "Chart",
      "level": 4,
      "bbox": {
        "x": 74.0,
        "y": 303.67,
        "w": 137.5,
        "h": 51.67
      }
    },
    {
      "nodeId": "panel_005",
      "parentId": "screen_0000",
      "type": "Panel",
      "level": 2,
      "bbox": {
        "x": 272.5,
        "y": 247.67,
        "w": 202.5,
        "h": 128.67
      }
    },
    {
      "nodeId": "panel_005_title",
      "parentId": "panel_005",
      "type": "Title",
      "level": 3,
      "bbox": {
        "x": 290.5,
        "y": 257.67,
        "w": 120,
        "h": 34
      }
    },
    {
      "nodeId": "panel_005_content",
      "parentId": "panel_005",
      "type": "Map",
      "level": 4,
      "bbox": {
        "x": 294.5,
        "y": 305.67,
        "w": 158.5,
        "h": 50.67
      }
    },
    {
      "nodeId": "panel_006",
      "parentId": "screen_0000",
      "type": "Panel",
      "level": 2,
      "bbox": {
        "x": 489.0,
        "y": 240.67,
        "w": 186.5,
        "h": 100.67
      }
    },
    {
      "nodeId": "panel_006_title",
      "parentId": "panel_006",
      "type": "Title",
      "level": 3,
      "bbox": {
        "x": 507.0,
        "y": 250.67,
        "w": 120,
        "h": 34
      }
    },
    {
      "nodeId": "panel_006_content",
      "parentId": "panel_006",
      "type": "MetricCard",
      "level": 4,
      "bbox": {
        "x": 511.0,
        "y": 298.67,
        "w": 142.5,
        "h": 22.67
      }
    },
    {
      "nodeId": "panel_007",
      "parentId": "screen_0000",
      "type": "Panel",
      "level": 2,
      "bbox": {
        "x": 710.5,
        "y": 253.67,
        "w": 190.5,
        "h": 126.67
      }
    },
    {
      "nodeId": "panel_007_title",
      "parentId": "panel_007",
      "type": "Title",
      "level": 3,
      "bbox": {
        "x": 728.5,
        "y": 263.67,
        "w": 120,
        "h": 34
      }
    },
    {
      "nodeId": "panel_007_content",
      "parentId": "panel_007",
      "type": "Chart",
      "level": 4,
      "bbox": {
        "x": 732.5,
        "y": 311.67,
        "w": 146.5,
        "h": 48.67
      }
    },
    {
      "nodeId": "panel_008",
      "parentId": "screen_0000",
      "type": "Panel",
      "level": 2,
      "bbox": {
        "x": 55.0,
        "y": 385.33,
        "w": 188.5,
        "h": 96.67
      }
    },
    {
      "nodeId": "panel_008_title",
      "parentId": "panel_008",
      "type": "Title",
      "level": 3,
      "bbox": {
        "x": 73.0,
        "y": 395.33,
        "w": 120,
        "h": 34
      }
    },
    {
      "nodeId": "panel_008_content",
      "parentId": "panel_008",
      "type": "Chart",
      "level": 4,
      "bbox": {
        "x": 77.0,
        "y": 443.33,
        "w": 144.5,
        "h": 18.67
      }
    },
    {
      "nodeId": "panel_009",
      "parentId": "screen_0000",
      "type": "Panel",
      "level": 2,
      "bbox": {
        "x": 260.5,
        "y": 384.33,
        "w": 206.5,
        "h": 109.67
      }
    },
    {
      "nodeId": "panel_009_title",
      "parentId": "panel_009",
      "type": "Title",
      "level": 3,
      "bbox": {
        "x": 278.5,
        "y": 394.33,
        "w": 120,
        "h": 34
      }
    },
    {
      "nodeId": "panel_009_content",
      "parentId": "panel_009",
      "type": "MetricCard",
      "level": 4,
      "bbox": {
        "x": 282.5,
        "y": 442.33,
        "w": 162.5,
        "h": 31.67
      }
    },
    {
      "nodeId": "panel_010",
      "parentId": "screen_0000",
      "type": "Panel",
      "level": 2,
      "bbox": {
        "x": 489.0,
        "y": 392.33,
        "w": 180.5,
        "h": 117.67
      }
    },
    {
      "nodeId": "panel_010_title",
      "parentId": "panel_010",
      "type": "Title",
      "level": 3,
      "bbox": {
        "x": 507.0,
        "y": 402.33,
        "w": 120,
        "h": 34
      }
    },
    {
      "nodeId": "panel_010_content",
      "parentId": "panel_010",
      "type": "Map",
      "level": 4,
      "bbox": {
        "x": 511.0,
        "y": 450.33,
        "w": 136.5,
        "h": 39.67
      }
    },
    {
      "nodeId": "panel_011",
      "parentId": "screen_0000",
      "type": "Panel",
      "level": 2,
      "bbox": {
        "x": 706.5,
        "y": 384.33,
        "w": 214.5,
        "h": 111.67
      }
    },
    {
      "nodeId": "panel_011_title",
      "parentId": "panel_011",
      "type": "Title",
      "level": 3,
      "bbox": {
        "x": 724.5,
        "y": 394.33,
        "w": 120,
        "h": 34
      }
    },
    {
      "nodeId": "panel_011_content",
      "parentId": "panel_011",
      "type": "MetricCard",
      "level": 4,
      "bbox": {
        "x": 728.5,
        "y": 442.33,
        "w": 170.5,
        "h": 33.67
      }
    }
  ]
}