{
  "width": 960,
  "height": 540,
  "nodes": [
    {
      "nodeId": "TextCommon_000",
      "parentId": "screen_0000",
      "type": "Title",
      "componentId": "TextCommon",
      "level": 3,
      "bbox": {
        "x": 518.03,
        "y": 469.3,
        "w": 235.63,
        "h": 38.38
      }
    },
    {
      "nodeId": "LineGradients_001",
      "parentId": "screen_0000",
      "type": "Chart",
      "componentId": "LineGradients",
      "level": 4,
      "bbox": {
        "x": 172.34,
        "y": 214.33,
        "w": 304.24,
        "h": 102.23
      }
    },
    {
      "nodeId": "Pie3DRingRegion_002",
      "parentId": "screen_0000",
      "type": "Chart",
      "componentId": "Pie3DRingRegion",
      "level": 4,
      "bbox": {
        "x": 691.68,
        "y": 86.17,
        "w": 184.91,
        "h": 146.39
      }
    },
    {
      "nodeId": "Decorates04_003",
      "parentId": "screen_0000",
      "type": "Decorate",
      "componentId": "Decorates04",
      "level": 3,
      "bbox": {
        "x": 664.77,
        "y": 352.04,
        "w": 170.79,
        "h": 26.21
      }
    },
    {
      "nodeId": "KeySecurity3D_004",
      "parentId": "screen_0000",
      "type": "Map",
      "componentId": "KeySecurity3D",
      "level": 4,
      "bbox": {
        "x": 223.72,
        "y": 383.27,
        "w": 258.56,
        "h": 124.96
      }
    },
    {
      "nodeId": "Border11_005",
      "parentId": "screen_0000",
      "type": "Border",
      "componentId": "Border11",
      "level": 3,
      "bbox": {
        "x": 403.46,
        "y": 79.44,
        "w": 281.96,
        "h": 180.44
      }
    },
    {
      "nodeId": "Graph_006",
      "parentId": "screen_0000",
      "type": "Chart",
      "componentId": "Graph",
      "level": 4,
      "bbox": {
        "x": 586.96,
        "y": 220.85,
        "w": 176.46,
        "h": 131.95
      }
    },
    {
      "nodeId": "VChartFunnel_007",
      "parentId": "screen_0000",
      "type": "Chart",
      "componentId": "VChartFunnel",
      "level": 4,
      "bbox": {
        "x": 171.14,
        "y": 81.92,
        "w": 182.09,
        "h": 160.2
      }
    },
    {
      "nodeId": "Process_008",
      "parentId": "screen_0000",
      "type": "MetricCard",
      "componentId": "Process",
      "level": 4,
      "bbox": {
        "x": 34.14,
        "y": 296.21,
        "w": 289.07,
        "h": 99.15
      }
    },
    {
      "nodeId": "Border03_009",
      "parentId": "screen_0000",
      "type": "Border",
      "componentId": "Border03",
      "level": 3,
      "bbox": {
        "x": 296.59,
        "y": 289.67,
        "w": 265.52,
        "h": 121.91
      }
    },
    {
      "nodeId": "PipelineV_010",
      "parentId": "screen_0000",
      "type": "Chart",
      "componentId": "PipelineV",
      "level": 4,
      "bbox": {
        "x": 557.31,
        "y": 374.12,
        "w": 220.37,
        "h": 90.44
      }
    },
    {
      "nodeId": "title1_011",
      "parentId": "screen_0000",
      "type": "Title",
      "componentId": "title1",
      "level": 3,
      "bbox": {
        "x": 775.72,
        "y": 226.72,
        "w": 153.63,
        "h": 30.28
      }
    }
  ]
}