{
  "width": 960,
  "height": 540,
  "nodes": [
    {
      "nodeId": "Border11_000",
      "parentId": "screen_0000",
      "type": "Border",
      "componentId": "Border11",
      "level": 3,
      "bbox": {
        "x": 647.93,
        "y": 217.31,
        "w": 281.27,
        "h": 145.8
      }
    },
    {
      "nodeId": "AlarmList_001",
      "parentId": "screen_0000",
      "type": "Table",
      "componentId": "AlarmList",
      "level": 4,
      "bbox": {
        "x": 700.97,
        "y": 105.52,
        "w": 218.08,
        "h": 125.88
      }
    },
    {
      "nodeId": "VChartLine_002",
      "parentId": "screen_0000",
      "type": "Chart",
      "componentId": "VChartLine",
      "level": 4,
      "bbox": {
        "x": 292.38,
        "y": 116.99,
        "w": 214.76,
        "h": 162.11
      }
    },
    {
      "nodeId": "Pie3DMultiLayer_003",
      "parentId": "screen_0000",
      "type": "Chart",
      "componentId": "Pie3DMultiLayer",
      "level": 4,
      "bbox": {
        "x": 160.38,
        "y": 360.32,
        "w": 280.13,
        "h": 153.98
      }
    },
    {
      "nodeId": "VChartPie_004",
      "parentId": "screen_0000",
      "type": "Chart",
      "componentId": "VChartPie",
      "level": 4,
      "bbox": {
        "x": 433.4,
        "y": 347.06,
        "w": 273.82,
        "h": 121.98
      }
    },
    {
      "nodeId": "Border14_005",
      "parentId": "screen_0000",
      "type": "Border",
      "componentId": "Border14",
      "level": 3,
      "bbox": {
        "x": 189.97,
        "y": 260.27,
        "w": 345.19,
        "h": 124.91
      }
    },
    {
      "nodeId": "Funnel_006",
      "parentId": "screen_0000",
      "type": "Chart",
      "componentId": "Funnel",
      "level": 4,
      "bbox": {
        "x": 546.0,
        "y": 64.83,
        "w": 230.07,
        "h": 89.84
      }
    },
    {
      "nodeId": "FullScreen_007",
      "parentId": "screen_0000",
      "type": "Decorate",
      "componentId": "FullScreen",
      "level": 3,
      "bbox": {
        "x": 78.45,
        "y": 135.62,
        "w": 244.41,
        "h": 163.49
      }
    },
    {
      "nodeId": "MapBase_008",
      "parentId": "screen_0000",
      "type": "Map",
      "componentId": "MapBase",
      "level": 4,
      "bbox": {
        "x": 510.7,
        "y": 115.53,
        "w": 256.62,
        "h": 122.66
      }
    },
    {
      "nodeId": "VChartPercentArea_009",
      "parentId": "screen_0000",
      "type": "Chart",
      "componentId": "VChartPercentArea",
      "level": 4,
      "bbox": {
        "x": 397.04,
        "y": 308.2,
        "w": 325.09,
        "h": 160.66
      }
    },
    {
      "nodeId": "Border02_010",
      "parentId": "screen_0000",
      "type": "Border",
      "componentId": "Border02",
      "level": 3,
      "bbox": {
        "x": 65.49,
        "y": 77.06,
        "w": 292.89,
        "h": 192.89
      }
    },
    {
      "nodeId": "TextGradient_011",
      "parentId": "screen_0000",
      "type": "Title",
      "componentId": "TextGradient",
      "level": 3,
      "bbox": {
        "x": 455.49,
        "y": 482.2,
        "w": 170.97,
        "h": 30.09
      }
    }
  ]
}